{
  "main": {
    "id": "6259d8a43f3e81a7",
    "type": "split",
    "children": [
      {
        "id": "d74691035db739ee",
        "type": "tabs",
        "children": [
          {
            "id": "25b6f868e0b6162e",
            "type": "leaf",
            "state": {
              "type": "markdown",
              "state": {
                "file": "Jokers/Jokers.md",
                "mode": "source",
                "source": false,
                "backlinks": false
              },
              "icon": "lucide-file",
              "title": "Jokers"
            }
          },
          {
            "id": "aed4eb35b47fa9cb",
            "type": "leaf",
            "state": {
              "type": "markdown",
              "state": {
                "file": "Jokers/3. Rare Jokers/127. The Idol.md",
                "mode": "source",
                "source": false,
                "backlinks": false
              },
              "icon": "lucide-file",
              "title": "127. The Idol"
            }
          }
        ]
      }
    ],
    "direction": "vertical"
  },
  "left": {
    "id": "73fb7b5811c63b8d",
    "type": "split",
    "children": [
      {
        "id": "a8d979826fd7bd7b",
        "type": "tabs",
        "children": [
          {
            "id": "ebfeadcbe7ed363a",
            "type": "leaf",
            "state": {
              "type": "file-explorer",
              "state": {
                "sortOrder": "alphabetical",
                "autoReveal": false
              },
              "icon": "lucide-folder-closed",
              "title": "Files"
            }
          },
          {
            "id": "9f14f7fd07a2be69",
            "type": "leaf",
            "state": {
              "type": "search",
              "state": {
                "query": "",
                "matchingCase": false,
                "explainSearch": false,
                "collapseAll": false,
                "extraContext": false,
                "sortOrder": "alphabetical"
              },
              "icon": "lucide-search",
              "title": "Search"
            }
          },
          {
            "id": "0c44d621449b39cf",
            "type": "leaf",
            "state": {
              "type": "bookmarks",
              "state": {},
              "icon": "lucide-bookmark",
              "title": "Bookmarks"
            }
          }
        ]
      }
    ],
    "direction": "horizontal",
    "width": 300
  },
  "right": {
    "id": "1ef7e3987a21f2b6",
    "type": "split",
    "children": [
      {
        "id": "5add0ce425a5fa9f",
        "type": "tabs",
        "children": [
          {
            "id": "eb854a819f3649d6",
            "type": "leaf",
            "state": {
              "type": "outline",
              "state": {
                "file": "Jokers/Jokers.md",
                "followCursor": false,
                "showSearch": false,
                "searchQuery": ""
              },
              "icon": "lucide-list",
              "title": "Outline of Jokers"
            }
          },
          {
            "id": "645ba6f79d9031fc",
            "type": "leaf",
            "state": {
              "type": "all-properties",
              "state": {
                "sortOrder": "frequency",
                "showSearch": false,
                "searchQuery": ""
              },
              "icon": "lucide-archive",
              "title": "All properties"
            }
          }
        ]
      }
    ],
    "direction": "horizontal",
    "width": 300,
    "collapsed": true
  },
  "left-ribbon": {
    "hiddenItems": {
      "switcher:Open quick switcher": false,
      "templates:Insert template": false,
      "command-palette:Open command palette": false,
      "graph:Open graph view": false,
      "obsidian-git:Open Git source control": false
    }
  },
  "active": "25b6f868e0b6162e",
  "lastOpenFiles": [
    "Terminology/Draw.md",
    "Tags/Tags.md",
    "The Table/The Table.md",
    "Jokers/3. Rare Jokers/127. The Idol.md",
    "Jokers/Jokers.md",
    "Game Phases/Game Phases.md",
    "Enhancements/Enhancements.md",
    "Editions/Editions.md",
    "Card Packs/Card Packs.md",
    "Arcana Cards/Arcana Cards.md",
    "Terminology/Purchases.md",
    "Terminology/Purchasing Power.md",
    "Terminology/Redistribution.md",
    "Terminology/Refunds.md",
    "Terminology/Scoring.md",
    "Terminology/The Big Pot.md",
    "Terminology/Personal Value.md",
    "Terminology/personal deck.md",
    "Terminology/Folding.md",
    "Terminology/Personal Pot.md",
    "Terminology/Draw Size.md",
    "Terminology/Card Value.md",
    "Vouchers/Vouchers.md",
    "Planet Cards/Planet Cards.md",
    "Playing Cards/Playing Cards.md",
    "Jokers/3. Rare Jokers/51. DNA.md",
    "Enhancements",
    "Card Packs",
    "Editions/Untitled",
    "Terminology",
    "Templates/Untitled",
    "Editions",
    "The Table",
    "Tags",
    "Planet Cards",
    "Playing Cards"
  ]
}